sts/__init__.py
sts/__main__.py
sts/cli.py
sts/data/htmlpage.tpl.html
sts/data/config/_default.json
sts/data/config/hk2s.json
sts/data/config/hk2t.json
sts/data/config/jp2t.json
sts/data/config/s2hk.json
sts/data/config/s2t.json
sts/data/config/s2tw.json
sts/data/config/s2twp.json
sts/data/config/t2hk.json
sts/data/config/t2jp.json
sts/data/config/t2s.json
sts/data/config/t2tw.json
sts/data/config/tw2s.json
sts/data/config/tw2sp.json
sts/data/config/tw2t.json
sts/data/dictionary/HKVariants.txt
sts/data/dictionary/HKVariantsRevPhrases.txt
sts/data/dictionary/JPShinjitaiCharacters.txt
sts/data/dictionary/JPShinjitaiPhrases.txt
sts/data/dictionary/JPVariants.txt
sts/data/dictionary/STCharacters.txt
sts/data/dictionary/STPhrases.txt
sts/data/dictionary/TSCharacters.txt
sts/data/dictionary/TSPhrases.txt
sts/data/dictionary/TWPhrases.txt
sts/data/dictionary/TWPhrasesRev.txt
sts/data/dictionary/TWVariants.txt
sts/data/dictionary/TWVariantsRevPhrases.txt
sts/data/scheme/st_multi.txt
sts/data/scheme/ts_multi.txt
sts/data/scheme/variant.txt
sts_lib-0.37.1.dist-info/licenses/LICENSE
sts_lib-0.37.1.dist-info/METADATA
sts_lib-0.37.1.dist-info/WHEEL
sts_lib-0.37.1.dist-info/entry_points.txt
sts_lib-0.37.1.dist-info/top_level.txt
sts_lib-0.37.1.dist-info/RECORD
