Metadata-Version: 2.4
Name: sts-lib
Version: 0.37.1
Summary: An open library for flexible simplified-traditional Chinese text conversion.
Author-email: Danny Lin <danny0838@gmail.com>
License: Apache 2.0
Project-URL: Homepage, https://github.com/danny0838/sts-lib
Classifier: Development Status :: 4 - Beta
Classifier: Operating System :: OS Independent
Classifier: Programming Language :: Python :: 3
Classifier: Programming Language :: Python :: 3 :: Only
Classifier: Programming Language :: Python :: 3.8
Classifier: Programming Language :: Python :: 3.9
Classifier: Programming Language :: Python :: 3.10
Classifier: Programming Language :: Python :: 3.11
Classifier: Programming Language :: Python :: 3.12
Classifier: Programming Language :: Python :: 3.13
Classifier: Programming Language :: Python :: 3.14
Requires-Python: ~=3.8
License-File: LICENSE
Provides-Extra: yaml
Requires-Dist: pyyaml>=5.0; extra == "yaml"
Dynamic: license
Dynamic: license-file
